preacher/__init__.py
preacher/app/__init__.py
preacher/app/cli/__init__.py
preacher/app/cli/app.py
preacher/app/cli/executor.py
preacher/app/cli/logging.py
preacher/app/cli/main.py
preacher/app/cli/option.py
preacher/compilation/__init__.py
preacher/compilation/argument.py
preacher/compilation/datetime.py
preacher/compilation/error.py
preacher/compilation/extraction/__init__.py
preacher/compilation/extraction/extraction.py
preacher/compilation/extraction/factory.py
preacher/compilation/parameter.py
preacher/compilation/request/__init__.py
preacher/compilation/request/factory.py
preacher/compilation/request/request.py
preacher/compilation/request/request_body.py
preacher/compilation/request/url_param.py
preacher/compilation/scenario/__init__.py
preacher/compilation/scenario/case.py
preacher/compilation/scenario/factory.py
preacher/compilation/scenario/integration.py
preacher/compilation/scenario/scenario.py
preacher/compilation/util/__init__.py
preacher/compilation/util/functional.py
preacher/compilation/util/type.py
preacher/compilation/verification/__init__.py
preacher/compilation/verification/description.py
preacher/compilation/verification/factory.py
preacher/compilation/verification/matcher.py
preacher/compilation/verification/predicate.py
preacher/compilation/verification/response.py
preacher/compilation/yaml/__init__.py
preacher/compilation/yaml/factory.py
preacher/compilation/yaml/integration.py
preacher/compilation/yaml/tag/__init__.py
preacher/compilation/yaml/tag/argument.py
preacher/compilation/yaml/tag/context.py
preacher/compilation/yaml/tag/datetime.py
preacher/core/__init__.py
preacher/core/context.py
preacher/core/datetime.py
preacher/core/extraction/__init__.py
preacher/core/extraction/analysis.py
preacher/core/extraction/error.py
preacher/core/extraction/extraction.py
preacher/core/extraction/impl/__init__.py
preacher/core/extraction/impl/jq_.py
preacher/core/extraction/impl/jq_engine.py
preacher/core/extraction/impl/key.py
preacher-0.15.11.dist-info/entry_points.txt
preacher-0.15.11.dist-info/LICENSE
preacher-0.15.11.dist-info/WHEEL
preacher-0.15.11.dist-info/METADATA
preacher-0.15.11.dist-info/RECORD
