Metadata-Version: 2.1
Name: preacher
Version: 0.15.11
Summary: Web API Verification without Coding.
Home-page: https://preacher.readthedocs.io/
License: MIT
Author: Yu Mochizuki
Author-email: ymoch.dev@gmail.com
Requires-Python: >=3.7,<4.0
Classifier: Development Status :: 4 - Beta
Classifier: Environment :: Console
Classifier: License :: OSI Approved :: MIT License
Classifier: Programming Language :: Python :: 3
Classifier: Programming Language :: Python :: 3.10
Classifier: Programming Language :: Python :: 3.7
Classifier: Programming Language :: Python :: 3.8
Classifier: Programming Language :: Python :: 3.9
Classifier: Topic :: Software Development :: Testing
Classifier: Topic :: System :: Monitoring
Requires-Dist: Jinja2 (>=3.0.1,<4.0.0)
Requires-Dist: click (>=8.0.1,<9.0.0)
Requires-Dist: colorama (>=0.4.1,<0.5.0)
Requires-Dist: jq (>=1.1.2,<2.0.0)
Requires-Dist: lxml (>=4.4,<5.0)
Requires-Dist: pluggy (>=1.0.0,<2.0.0)
Requires-Dist: pyhamcrest (>=2.0,<3.0)
Requires-Dist: python-dateutil (>=2.8.1,<3.0.0)
Requires-Dist: requests (>=2.21,<3.0)
Requires-Dist: yamlen (>=0.2,<0.3)
Project-URL: Repository, https://github.com/ymoch/preacher
